bftc/__init__.py
bftc/code_generator.py
bftc/tokenizer.py
bftc/tokens.py
bftc/transpiler.py
bftc-2.0.0.dist-info/LICENSE
bftc-2.0.0.dist-info/WHEEL
bftc-2.0.0.dist-info/METADATA
bftc-2.0.0.dist-info/RECORD
