Metadata-Version: 2.1
Name: bftc
Version: 2.0.0
Summary: Simple Brainfuck to C transpiler
Home-page: https://github.com/ilhomidin/bftc
Author: Ilxomidin Bakhoraliev
Author-email: itilhomidin@yandex.com
Classifier: License :: OSI Approved :: MIT License
Classifier: Programming Language :: Python :: 3.10
